squid_py/__init__.py
squid_py/config.py
squid_py/config_provider.py
squid_py/agreement_events/__init__.py
squid_py/agreement_events/accessSecretStore.py
squid_py/agreement_events/escrowAccessSecretStoreTemplate.py
squid_py/assets/__init__.py
squid_py/assets/asset_consumer.py
squid_py/brizo/__init__.py
squid_py/brizo/brizo.py
squid_py/brizo/brizo_provider.py
squid_py/data_store/__init__.py
squid_py/data_store/auth_tokens.py
squid_py/models/__init__.py
squid_py/models/algorithm_metadata.py
squid_py/ocean/__init__.py
squid_py/ocean/keeper.py
squid_py/ocean/ocean.py
squid_py/ocean/ocean_accounts.py
squid_py/ocean/ocean_agreements.py
squid_py/ocean/ocean_assets.py
squid_py/ocean/ocean_auth.py
squid_py/ocean/ocean_compute.py
squid_py/ocean/ocean_conditions.py
squid_py/ocean/ocean_providers.py
squid_py/ocean/ocean_secret_store.py
squid_py/ocean/ocean_services.py
squid_py/ocean/ocean_templates.py
squid_py/ocean/ocean_tokens.py
squid_py/secret_store/__init__.py
squid_py/secret_store/secret_store.py
squid_py/secret_store/secret_store_provider.py
squid_py-0.9.3.dist-info/LICENSE
squid_py-0.9.3.dist-info/METADATA
squid_py-0.9.3.dist-info/WHEEL
squid_py-0.9.3.dist-info/top_level.txt
squid_py-0.9.3.dist-info/RECORD
